Metadata-Version: 2.1
Name: pdfls
Version: 0.1
Summary: pdfls is a small utility to debug a PDF file.
Home-page: https://github.com/metebalci/pdfls
Author: Mete Balci
Author-email: metebalci@gmail.com
License: GPLv3
Keywords: pdf
Platform: UNKNOWN
Classifier: Development Status :: 3 - Alpha
Classifier: Environment :: Console
Classifier: Intended Audience :: Science/Research
Classifier: License :: OSI Approved :: GNU General Public License v3 (GPLv3)
Classifier: Topic :: Utilities
Classifier: Programming Language :: Python :: 3.6
